dj_compression_middleware/__init__.py
dj_compression_middleware/br.py
dj_compression_middleware/decorators.py
dj_compression_middleware/middleware.py
dj_compression_middleware/zstd.py
dj_compression_middleware-0.0.2.dist-info/WHEEL
dj_compression_middleware-0.0.2.dist-info/METADATA
dj_compression_middleware-0.0.2.dist-info/RECORD
