Metadata-Version: 2.3
Name: dj-compression-middleware
Version: 0.0.2
Summary: Django middleware to compress responses with gzip, brotli and zstd.
Author: Mathieu Hinderyckx
Author-email: Mathieu Hinderyckx <mathieu.hinderyckx@gmail.com>
Classifier: Framework :: Django
Classifier: Framework :: Django :: 4.0
Classifier: Framework :: Django :: 4.1
Classifier: Framework :: Django :: 4.2
Classifier: Framework :: Django :: 5.0
Classifier: Framework :: Django :: 5.1
Classifier: Framework :: Django :: 5.2
Classifier: Intended Audience :: Developers
Classifier: License :: OSI Approved :: Mozilla Public License 2.0 (MPL 2.0)
Classifier: Natural Language :: English
Classifier: Operating System :: OS Independent
Classifier: Programming Language :: Python :: 3
Classifier: Programming Language :: Python :: 3.9
Classifier: Programming Language :: Python :: 3.10
Classifier: Programming Language :: Python :: 3.11
Classifier: Programming Language :: Python :: 3.12
Classifier: Programming Language :: Python :: 3.13
Classifier: Programming Language :: Python :: 3.14
Classifier: Programming Language :: Python :: Implementation :: CPython
Classifier: Programming Language :: Python :: Implementation :: PyPy
Requires-Dist: brotli>=1.1.0 ; platform_python_implementation != 'PyPy'
Requires-Dist: brotlipy>=0.7.0 ; platform_python_implementation == 'PyPy'
Requires-Dist: django>=4.0
Requires-Dist: zstandard>=0.24.0
Requires-Python: >=3.10, <3.15
